[
    {
        "link": "https://www.facebook.com/marketplace/item/1266149877951864/?ref=search&referral_code=null&referral_story_type=post&tracking=browse_serp%3A95406b26-d34d-4a69-9607-eae810e7b0b9&__tn__=!%3AD",
        "price": "$645",
        "name": "Private room for rent",
        "location": "Gainesville, FL"
    },
    {
        "link": "https://www.facebook.com/marketplace/item/8596626967112988/?ref=search&referral_code=null&referral_story_type=post&tracking=browse_serp%3A95406b26-d34d-4a69-9607-eae810e7b0b9&__tn__=!%3AD",
        "price": "$500",
        "name": "1 Bed 1 Bath Room only",
        "location": "Gainesville, FL"
    },
    {
        "link": "https://www.facebook.com/marketplace/item/1402538154351202/?ref=search&referral_code=null&referral_story_type=post&tracking=browse_serp%3A95406b26-d34d-4a69-9607-eae810e7b0b9&__tn__=!%3AD",
        "price": "$400",
        "name": "1 Bed 1 Bath Apartment/condo",
        "location": "Gainesville, FL"
    },
    {
        "link": "https://www.facebook.com/marketplace/item/585753057755971/?ref=search&referral_code=null&referral_story_type=post&tracking=browse_serp%3A95406b26-d34d-4a69-9607-eae810e7b0b9&__tn__=!%3AD",
        "price": "$870",
        "name": "3 beds 2 baths House",
        "location": "Gainesville, FL"
    },
    {
        "link": "https://www.facebook.com/marketplace/item/1123324689018023/?ref=search&referral_code=null&referral_story_type=post&tracking=browse_serp%3A95406b26-d34d-4a69-9607-eae810e7b0b9&__tn__=!%3AD",
        "price": "$610",
        "name": "Private room for rent",
        "location": "Gainesville, FL"
    },
    {
        "link": "https://www.facebook.com/marketplace/item/8809759315820452/?ref=search&referral_code=null&referral_story_type=post&tracking=browse_serp%3A95406b26-d34d-4a69-9607-eae810e7b0b9&__tn__=!%3AD",
        "price": "$1,800",
        "name": "House sublease",
        "location": "Gainesville, FL"
    },
    {
        "link": "https://www.facebook.com/marketplace/item/612077221182143/?ref=search&referral_code=null&referral_story_type=post&tracking=browse_serp%3A95406b26-d34d-4a69-9607-eae810e7b0b9&__tn__=!%3AD",
        "price": "$650",
        "name": "1 Bed 1 Bath Apartment/condo",
        "location": "Gainesville, FL"
    },
    {
        "link": "https://www.facebook.com/marketplace/item/576764191862375/?ref=search&referral_code=null&referral_story_type=post&tracking=browse_serp%3A95406b26-d34d-4a69-9607-eae810e7b0b9&__tn__=!%3AD",
        "price": "$1,030",
        "name": "2 beds 1 bath House",
        "location": "Gainesville, FL"
    },
    {
        "link": "https://www.facebook.com/marketplace/item/1745187642997410/?ref=search&referral_code=null&referral_story_type=post&tracking=browse_serp%3A95406b26-d34d-4a69-9607-eae810e7b0b9&__tn__=!%3AD",
        "price": "$625",
        "name": "2 Beds 2 Baths Apartment",
        "location": "Gainesville, FL"
    },
    {
        "link": "https://www.facebook.com/marketplace/item/603618862400213/?ref=search&referral_code=null&referral_story_type=post&tracking=browse_serp%3A95406b26-d34d-4a69-9607-eae810e7b0b9&__tn__=!%3AD",
        "price": "$1,350",
        "name": "3 Beds 2 Baths House",
        "location": "Gainesville, FL"
    },
    {
        "link": "https://www.facebook.com/marketplace/item/1443050337100383/?ref=search&referral_code=null&referral_story_type=post&tracking=browse_serp%3A95406b26-d34d-4a69-9607-eae810e7b0b9&__tn__=!%3AD",
        "price": "$599",
        "name": "1 Bed 1 Bath Apartment/condo",
        "location": "Gainesville, FL"
    },
    {
        "link": "https://www.facebook.com/marketplace/item/961754628729276/?ref=search&referral_code=null&referral_story_type=post&tracking=browse_serp%3A95406b26-d34d-4a69-9607-eae810e7b0b9&__tn__=!%3AD",
        "price": "$990",
        "name": "2 Beds 2 Baths Apartment",
        "location": "Gainesville, FL"
    },
    {
        "link": "https://www.facebook.com/marketplace/item/2043833842727085/?ref=search&referral_code=null&referral_story_type=post&tracking=browse_serp%3A95406b26-d34d-4a69-9607-eae810e7b0b9&__tn__=!%3AD",
        "price": "$750",
        "name": "2 Beds 1 Bath House",
        "location": "Gainesville, FL"
    },
    {
        "link": "https://www.facebook.com/marketplace/item/1622466695067095/?ref=search&referral_code=null&referral_story_type=post&tracking=browse_serp%3A95406b26-d34d-4a69-9607-eae810e7b0b9&__tn__=!%3AD",
        "price": "$1,050",
        "name": "3 Beds 2 Baths House",
        "location": "Gainesville, FL"
    },
    {
        "link": "https://www.facebook.com/marketplace/item/980124920655480/?ref=search&referral_code=null&referral_story_type=post&tracking=browse_serp%3A95406b26-d34d-4a69-9607-eae810e7b0b9&__tn__=!%3AD",
        "price": "$983",
        "name": "2 Beds 1 Bath - House",
        "location": "Gainesville, FL"
    },
    {
        "link": "https://www.facebook.com/marketplace/item/1118689353378603/?ref=search&referral_code=null&referral_story_type=post&tracking=browse_serp%3A95406b26-d34d-4a69-9607-eae810e7b0b9&__tn__=!%3AD",
        "price": "$1,320",
        "name": "2 Beds 2 Baths House",
        "location": "Gainesville, FL"
    },
    {
        "link": "https://www.facebook.com/marketplace/item/954557729597156/?ref=search&referral_code=null&referral_story_type=post&tracking=browse_serp%3A95406b26-d34d-4a69-9607-eae810e7b0b9&__tn__=!%3AD",
        "price": "$1,200",
        "name": "3 Beds 2 Baths House",
        "location": "Gainesville, FL"
    },
    {
        "link": "https://www.facebook.com/marketplace/item/613949731577765/?ref=search&referral_code=null&referral_story_type=post&tracking=browse_serp%3A95406b26-d34d-4a69-9607-eae810e7b0b9&__tn__=!%3AD",
        "price": "$625",
        "name": "Studio 1 bath Flat",
        "location": "Gainesville, FL"
    },
    {
        "link": "https://www.facebook.com/marketplace/item/602295039052011/?ref=search&referral_code=null&referral_story_type=post&tracking=browse_serp%3A95406b26-d34d-4a69-9607-eae810e7b0b9&__tn__=!%3AD",
        "price": "$700",
        "name": "3 beds 2 baths House",
        "location": "Gainesville, FL"
    },
    {
        "link": "https://www.facebook.com/marketplace/item/575192311933413/?ref=search&referral_code=null&referral_story_type=post&tracking=browse_serp%3A95406b26-d34d-4a69-9607-eae810e7b0b9&__tn__=!%3AD",
        "price": "$175",
        "name": "Oversized large warehouse self-storage with drive-up access and power amenities.",
        "location": "Gainesville, FL"
    },
    {
        "link": "https://www.facebook.com/marketplace/item/645532984575774/?ref=search&referral_code=null&referral_story_type=post&tracking=browse_serp%3A95406b26-d34d-4a69-9607-eae810e7b0b9&__tn__=!%3AD",
        "price": "$1,269",
        "name": "2 Beds 2 Baths House",
        "location": "Gainesville, FL"
    },
    {
        "link": "https://www.facebook.com/marketplace/item/1313976793076434/?ref=search&referral_code=null&referral_story_type=post&tracking=browse_serp%3A95406b26-d34d-4a69-9607-eae810e7b0b9&__tn__=!%3AD",
        "price": "$850",
        "name": "3 Beds 1 Bath House",
        "location": "Gainesville, FL"
    }
]